simple_multiprocessing/__init__.py
simple_multiprocessing/_multi_task.py
simple_multiprocessing/multi_process.py
simple_multiprocessing/multi_thread.py
simple_multiprocessing/simple_multiprocessing.py
simple_multiprocessing/models/__init__.py
simple_multiprocessing/models/constants.py
simple_multiprocessing/models/task.py
simple_multiprocessing/models/enums/__init__.py
simple_multiprocessing/utils/__init__.py
simple_multiprocessing/utils/utils.py
simple_multiprocessing-0.0.15.dist-info/LICENSE
simple_multiprocessing-0.0.15.dist-info/METADATA
simple_multiprocessing-0.0.15.dist-info/WHEEL
simple_multiprocessing-0.0.15.dist-info/top_level.txt
simple_multiprocessing-0.0.15.dist-info/RECORD
